{
    "id": "neo4j",
    "version": "0.0.1",
    "meta": {
        "label": "Neo4j",
        "description": "Interacting with the Neo4j graph database",
        "author": "Dataiku (Thomas)",
        "icon": "icon-folder-close",
        "licenseInfo": "Apache Software License",
        "url": "https://www.dataiku.com/dss/plugins/info/neo4j.html",
        "tags": ["Graph", "Connector"]
    },
    "params": [
        {
            "name": "neo4jUri",
            "label": "URI",
            "description": "URI of the Neo4j database (bolt://...)",
            "type": "STRING",
            "mandatory": true
        },
        {
            "name": "neo4jUsername",
            "label": "Username",
            "description": "Username to connect to the Neo4j database",
            "type": "STRING",
            "mandatory": true
        },
        {
            "name": "neo4jPassword",
            "label": "Password",
            "description": "Password to connect to the Neo4j database",
            "type": "PASSWORD",
            "mandatory": true
        }
    ]
}